Mail_Generator/__init__.py
Mail_Generator/main.py
mail_Generator-0.2.2.dist-info/LICENSE
mail_Generator-0.2.2.dist-info/METADATA
mail_Generator-0.2.2.dist-info/WHEEL
mail_Generator-0.2.2.dist-info/entry_points.txt
mail_Generator-0.2.2.dist-info/top_level.txt
mail_Generator-0.2.2.dist-info/RECORD
