Metadata-Version: 2.1
Name: mail-Generator
Version: 0.2.2
Summary: A Python package that provides an easy-to-use interface for creating and managing email addresses
Home-page: https://github.com/matthieuEv/mail-generator
License-File: LICENSE
Requires-Dist: mailslurp-client
